{
  "cuda_graph": {
    "cuda_graph_events_count": 0,
    "cuda_graph_events_present": false,
    "event_names": [],
    "kernel_graph_node_nonnull_count": 787320,
    "runtime_graph_api": [
      {
        "count": 73489,
        "duration_s": 0.04130136,
        "name": "cudaStreamGetCaptureInfo_v2_v11030"
      },
      {
        "count": 2880,
        "duration_s": 0.946761185,
        "name": "cudaThreadExchangeStreamCaptureMode_v10010"
      },
      {
        "count": 531,
        "duration_s": 0.00033023,
        "name": "cudaStreamUpdateCaptureDependencies_v11030"
      },
      {
        "count": 264,
        "duration_s": 0.000217814,
        "name": "cudaGraphAddDependencies_v10000"
      },
      {
        "count": 264,
        "duration_s": 0.000540968,
        "name": "cudaGraphAddEventRecordNode_v11010"
      },
      {
        "count": 264,
        "duration_s": 0.000238112,
        "name": "cudaGraphRetainUserObject_v11030"
      },
      {
        "count": 30,
        "duration_s": 1.560166839,
        "name": "cudaGraphLaunch_v10000"
      },
      {
        "count": 3,
        "duration_s": 0.171659331,
        "name": "cudaGraphExecDestroy_v10000"
      },
      {
        "count": 3,
        "duration_s": 0.0364609,
        "name": "cudaGraphDestroy_v10000"
      },
      {
        "count": 3,
        "duration_s": 0.619923992,
        "name": "cudaGraphInstantiateWithFlags_v11040"
      },
      {
        "count": 3,
        "duration_s": 0.000386645,
        "name": "cudaGraphGetNodes_v10000"
      },
      {
        "count": 3,
        "duration_s": 0.00535411,
        "name": "cudaStreamEndCapture_v10000"
      },
      {
        "count": 3,
        "duration_s": 1.2694e-05,
        "name": "cudaStreamBeginCapture_v10000"
      }
    ]
  },
  "lite": false,
  "nvtx_window": {
    "graph_trace": {
      "present": false
    },
    "kernel": {
      "count": 454637,
      "duration_s": 23.830082475,
      "present": true
    },
    "memcpy": {
      "bytes": 237821036,
      "count": 34984,
      "duration_s": 0.064237195,
      "present": true
    },
    "memset": {
      "count": 121,
      "duration_s": 0.000193438,
      "present": true
    },
    "nccl_kernel": {
      "count": 1408,
      "duration_s": 0.193262947,
      "present": true
    },
    "nccl_nvtx": {
      "count": 88,
      "end_ns": 125472305217,
      "present": true,
      "start_ns": 104651857792
    },
    "runtime": {
      "count": 97097,
      "duration_s": 23.855674062,
      "present": true
    },
    "sync": {
      "count": 1114,
      "duration_s": 22.496348422,
      "present": true
    },
    "top_kernels": [
      {
        "count": 688,
        "duration_s": 9.525333168,
        "name": "_grouped_fp4_w13_kernel"
      },
      {
        "count": 688,
        "duration_s": 6.472419518,
        "name": "_grouped_fp4_linear_kernel"
      },
      {
        "count": 656,
        "duration_s": 2.299561462,
        "name": "void <unnamed>::sparse_attention_kernel<(bool)1>(<unnamed>::SparseAttentionParams)"
      },
      {
        "count": 336,
        "duration_s": 0.932697162,
        "name": "_indexer_bf16_logits_kernel"
      },
      {
        "count": 34084,
        "duration_s": 0.76778334,
        "name": "void at::native::unrolled_elementwise_kernel<at::native::direct_copy_kernel_cuda(at::TensorIteratorBase &)::[lambda() (instance 3)]::operator ()() const::[lambda() (instance 7)]::operator ()() const::[lambda(float) (instance 1)], std::array<char *, (unsigned long)2>, (int)4, TrivialOffsetCalculator<(int)1, unsigned int>, TrivialOffsetCalculator<(int)1, unsigned int>, at::native::memory::LoadWithCast<(int)1>, at::native::memory::StoreWithCast<(int)1>>(int, T1, T2, T4, T5, T6, T7)"
      },
      {
        "count": 4144,
        "duration_s": 0.593672976,
        "name": "void at::native::elementwise_kernel<(int)128, (int)4, void at::native::gpu_kernel_impl_nocast<at::native::BinaryFunctor<c10::BFloat16, c10::BFloat16, c10::BFloat16, at::native::binary_internal::MulFunctor<float>>>(at::TensorIteratorBase &, const T1 &)::[lambda(int) (instance 1)]>(int, T3)"
      },
      {
        "count": 27876,
        "duration_s": 0.391053706,
        "name": "void at::native::elementwise_kernel<(int)128, (int)2, void at::native::gpu_kernel_impl_nocast<at::native::direct_copy_kernel_cuda(at::TensorIteratorBase &)::[lambda() (instance 3)]::operator ()() const::[lambda() (instance 7)]::operator ()() const::[lambda(float) (instance 1)]>(at::TensorIteratorBase &, const T1 &)::[lambda(int) (instance 1)]>(int, T3)"
      },
      {
        "count": 2768,
        "duration_s": 0.191368398,
        "name": "void at::native::reduce_kernel<(int)128, (int)4, at::native::ReduceOp<c10::BFloat16, at::native::func_wrapper_t<c10::BFloat16, at::native::sum_functor<c10::BFloat16, float, c10::BFloat16>::operator ()(at::TensorIterator &)::[lambda(float, float) (instance 1)]>, unsigned int, c10::BFloat16, (int)4, (int)4>>(T3)"
      },
      {
        "count": 59504,
        "duration_s": 0.169555527,
        "name": "void at::native::elementwise_kernel<(int)128, (int)2, void at::native::gpu_kernel_impl_nocast<at::native::BinaryFunctor<float, float, float, at::native::binary_internal::DivFunctor<float>>>(at::TensorIteratorBase &, const T1 &)::[lambda(int) (instance 1)]>(int, T3)"
      },
      {
        "count": 10096,
        "duration_s": 0.16761996,
        "name": "void at::native::vectorized_elementwise_kernel<(int)4, at::native::CUDAFunctor_add<float>, std::array<char *, (unsigned long)3>>(int, T2, T3)"
      },
      {
        "count": 15225,
        "duration_s": 0.157865722,
        "name": "void at::native::elementwise_kernel<(int)128, (int)2, void at::native::gpu_kernel_impl_nocast<at::native::BinaryFunctor<float, float, float, at::native::binary_internal::MulFunctor<float>>>(at::TensorIteratorBase &, const T1 &)::[lambda(int) (instance 1)]>(int, T3)"
      },
      {
        "count": 20292,
        "duration_s": 0.150753122,
        "name": "void at::native::vectorized_elementwise_kernel<(int)4, at::native::bfloat16_copy_kernel_cuda(at::TensorIteratorBase &)::[lambda(float) (instance 1)], std::array<char *, (unsigned long)2>>(int, T2, T3)"
      },
      {
        "count": 3808,
        "duration_s": 0.143044872,
        "name": "void at::native::vectorized_elementwise_kernel<(int)4, void at::native::<unnamed>::pow_tensor_scalar_kernel_impl<float, float>(at::TensorIteratorBase &, T2)::[lambda(float) (instance 1)], std::array<char *, (unsigned long)2>>(int, T2, T3)"
      },
      {
        "count": 688,
        "duration_s": 0.116205452,
        "name": "ncclDevKernel_AllReduce_Sum_f32_RING_LL(ncclDevKernelArgsStorage<(unsigned long)4096>)"
      },
      {
        "count": 255,
        "duration_s": 0.111091287,
        "name": "ampere_bf16_s16816gemm_bf16_128x256_ldg8_f2f_stages_64x3_tn"
      },
      {
        "count": 6139,
        "duration_s": 0.108991833,
        "name": "void at::native::vectorized_elementwise_kernel<(int)4, at::native::BinaryFunctor<float, float, float, at::native::binary_internal::MulFunctor<float>>, std::array<char *, (unsigned long)3>>(int, T2, T3)"
      },
      {
        "count": 28212,
        "duration_s": 0.097219828,
        "name": "void at::native::reduce_kernel<(int)128, (int)4, at::native::ReduceOp<float, at::native::func_wrapper_t<float, at::native::sum_functor<float, float, float>::operator ()(at::TensorIterator &)::[lambda(float, float) (instance 1)]>, unsigned int, float, (int)4, (int)4>>(T3)"
      },
      {
        "count": 87,
        "duration_s": 0.096796019,
        "name": "ampere_sgemm_32x128_tn"
      },
      {
        "count": 60928,
        "duration_s": 0.094277889,
        "name": "void at::native::vectorized_elementwise_kernel<(int)4, at::native::CUDAFunctorOnSelf_add<float>, std::array<char *, (unsigned long)2>>(int, T2, T3)"
      },
      {
        "count": 3808,
        "duration_s": 0.087226781,
        "name": "void at::native::reduce_kernel<(int)512, (int)1, at::native::ReduceOp<float, at::native::MeanOps<float, float, float, float>, unsigned int, float, (int)4, (int)4>>(T3)"
      }
    ],
    "top_nvtx": [
      {
        "count": 100,
        "end_ns": 128604426600,
        "name": "cub::DeviceSelect::Flagged",
        "start_ns": 103429823028
      },
      {
        "count": 100,
        "end_ns": 128604380734,
        "name": "cub::DeviceReduce::Sum",
        "start_ns": 103429770249
      },
      {
        "count": 87,
        "end_ns": 125471183244,
        "name": "ncclAllReduce",
        "start_ns": 104651857792
      },
      {
        "count": 32,
        "end_ns": 128477432384,
        "name": "Sampler",
        "start_ns": 125472448376
      },
      {
        "count": 17,
        "end_ns": 128605276163,
        "name": "cub::DeviceSelect::Unique",
        "start_ns": 103430130244
      },
      {
        "count": 16,
        "end_ns": 128423691722,
        "name": "cub::DeviceScan::InclusiveScan",
        "start_ns": 103431248330
      },
      {
        "count": 15,
        "end_ns": 128426170209,
        "name": "batch_prepare:decode:bs4",
        "start_ns": 125942836424
      },
      {
        "count": 15,
        "end_ns": 128477693083,
        "name": "batch_forward_enqueue:decode:bs4:padded4",
        "start_ns": 125947173767
      },
      {
        "count": 15,
        "end_ns": 128599763586,
        "name": "batch_forward:decode:bs4:padded4",
        "start_ns": 125947170170
      },
      {
        "count": 12,
        "end_ns": 128605240286,
        "name": "cub::DeviceRadixSort",
        "start_ns": 103429985012
      },
      {
        "count": 1,
        "end_ns": 128606115948,
        "name": "repeat:decode_throughput_bs8:0",
        "start_ns": 103427203746
      },
      {
        "count": 1,
        "end_ns": 125472305217,
        "name": "ncclAllGather",
        "start_ns": 125472253170
      },
      {
        "count": 1,
        "end_ns": 125471742602,
        "name": "dsv4.model.hc_head",
        "start_ns": 125471377798
      },
      {
        "count": 1,
        "end_ns": 104652164026,
        "name": "dsv4.model.hc_expand",
        "start_ns": 104652072344
      },
      {
        "count": 1,
        "end_ns": 125471931447,
        "name": "dsv4.model.final_norm",
        "start_ns": 125471757020
      },
      {
        "count": 1,
        "end_ns": 104652058087,
        "name": "dsv4.model.embed",
        "start_ns": 104651233962
      },
      {
        "count": 1,
        "end_ns": 125472409713,
        "name": "dsv4.lm_head",
        "start_ns": 125472034821
      },
      {
        "count": 1,
        "end_ns": 109077607539,
        "name": "dsv4.layer9.mlp_input_norm",
        "start_ns": 109077435676
      },
      {
        "count": 1,
        "end_ns": 109079723947,
        "name": "dsv4.layer9.mlp.shared",
        "start_ns": 109078577798
      },
      {
        "count": 1,
        "end_ns": 109078563571,
        "name": "dsv4.layer9.mlp.routed",
        "start_ns": 109077932498
      }
    ],
    "top_runtime": [
      {
        "count": 234,
        "duration_s": 20.179929481,
        "name": "cudaStreamSynchronize_v3020"
      },
      {
        "count": 33,
        "duration_s": 2.315219025,
        "name": "cudaDeviceSynchronize_v3020"
      },
      {
        "count": 15,
        "duration_s": 0.738431195,
        "name": "cudaGraphLaunch_v10000"
      },
      {
        "count": 60276,
        "duration_s": 0.36660802,
        "name": "cudaLaunchKernel_v7000"
      },
      {
        "count": 33049,
        "duration_s": 0.243744988,
        "name": "cudaMemcpyAsync_v3020"
      },
      {
        "count": 701,
        "duration_s": 0.005739396,
        "name": "cuLaunchKernelEx"
      },
      {
        "count": 566,
        "duration_s": 0.001545128,
        "name": "cudaEventQuery_v3020"
      },
      {
        "count": 352,
        "duration_s": 0.001517161,
        "name": "cudaEventRecord_v3020"
      },
      {
        "count": 193,
        "duration_s": 0.000805577,
        "name": "cudaEventRecordWithFlags_v11010"
      },
      {
        "count": 121,
        "duration_s": 0.000599627,
        "name": "cudaMemsetAsync_v3020"
      },
      {
        "count": 265,
        "duration_s": 0.000365563,
        "name": "cudaStreamWaitEvent_v3020"
      },
      {
        "count": 604,
        "duration_s": 0.000338078,
        "name": "cudaThreadExchangeStreamCaptureMode_v10010"
      },
      {
        "count": 318,
        "duration_s": 0.000307835,
        "name": "cudaStreamIsCapturing_v10000"
      },
      {
        "count": 89,
        "duration_s": 0.000189916,
        "name": "cudaEventCreateWithFlags_v3020"
      },
      {
        "count": 16,
        "duration_s": 0.000109995,
        "name": "cudaEventSynchronize_v3020"
      },
      {
        "count": 89,
        "duration_s": 8.319e-05,
        "name": "cudaEventDestroy_v3020"
      },
      {
        "count": 88,
        "duration_s": 8.0373e-05,
        "name": "cudaStreamGetCaptureInfo_v2_v11030"
      },
      {
        "count": 88,
        "duration_s": 5.9514e-05,
        "name": "cudaGetFuncBySymbol_v11000"
      }
    ],
    "window_found": true,
    "window_name": "repeat:decode_throughput_bs8:0",
    "window_ns": [
      103427203746,
      128606115948
    ]
  },
  "requested_nvtx_window": "repeat:decode_throughput_bs8:0",
  "sqlite_path": "/tmp/nsys_target07_2_mini_v1_moe_graph_capture_nvtx_node_trace_probe_4096x16_bs4_np72_batch4_warmup1_rank0.sqlite",
  "tables": [
    "ANALYSIS_DETAILS",
    "ANALYSIS_FILE",
    "CUDA_GRAPH_NODE_EVENTS",
    "CUPTI_ACTIVITY_KIND_CUDA_EVENT",
    "CUPTI_ACTIVITY_KIND_KERNEL",
    "CUPTI_ACTIVITY_KIND_MEMCPY",
    "CUPTI_ACTIVITY_KIND_MEMSET",
    "CUPTI_ACTIVITY_KIND_RUNTIME",
    "CUPTI_ACTIVITY_KIND_SYNCHRONIZATION",
    "DIAGNOSTIC_EVENT",
    "ENUM_CUDA_DEV_MEM_EVENT_OPER",
    "ENUM_CUDA_FUNC_CACHE_CONFIG",
    "ENUM_CUDA_KERNEL_LAUNCH_TYPE",
    "ENUM_CUDA_MEMCPY_OPER",
    "ENUM_CUDA_MEMPOOL_OPER",
    "ENUM_CUDA_MEMPOOL_TYPE",
    "ENUM_CUDA_MEM_KIND",
    "ENUM_CUDA_SHARED_MEM_LIMIT_CONFIG",
    "ENUM_CUDA_UNIF_MEM_ACCESS_TYPE",
    "ENUM_CUDA_UNIF_MEM_MIGRATION",
    "ENUM_CUPTI_STREAM_TYPE",
    "ENUM_CUPTI_SYNC_TYPE",
    "ENUM_D3D12_CMD_LIST_TYPE",
    "ENUM_D3D12_HEAP_FLAGS",
    "ENUM_D3D12_HEAP_TYPE",
    "ENUM_D3D12_PAGE_PROPERTY",
    "ENUM_DIAGNOSTIC_SEVERITY_LEVEL",
    "ENUM_DIAGNOSTIC_SOURCE_TYPE",
    "ENUM_DIAGNOSTIC_TIMESTAMP_SOURCE",
    "ENUM_DXGI_FORMAT",
    "ENUM_ETW_MEMORY_TRANSFER_TYPE",
    "ENUM_GPU_CTX_SWITCH",
    "ENUM_NET_DEVICE_ID",
    "ENUM_NET_IB_DEVICE_TYPE",
    "ENUM_NET_LINK_TYPE",
    "ENUM_NET_VENDOR_ID",
    "ENUM_NSYS_EVENT_CLASS",
    "ENUM_NSYS_EVENT_TYPE",
    "ENUM_NSYS_GENERIC_EVENT_FIELD_ETW_FLAGS",
    "ENUM_NSYS_GENERIC_EVENT_FIELD_ETW_PROPERTY",
    "ENUM_NSYS_GENERIC_EVENT_FIELD_ETW_TYPE",
    "ENUM_NSYS_GENERIC_EVENT_FIELD_TYPE",
    "ENUM_NSYS_GENERIC_EVENT_GROUP",
    "ENUM_NSYS_GENERIC_EVENT_SOURCE",
    "ENUM_NVDRIVER_EVENT_ID",
    "ENUM_OPENACC_DEVICE",
    "ENUM_OPENACC_EVENT_KIND",
    "ENUM_OPENGL_DEBUG_SEVERITY",
    "ENUM_OPENGL_DEBUG_SOURCE",
    "ENUM_OPENGL_DEBUG_TYPE",
    "ENUM_OPENMP_DISPATCH",
    "ENUM_OPENMP_EVENT_KIND",
    "ENUM_OPENMP_MUTEX",
    "ENUM_OPENMP_SYNC_REGION",
    "ENUM_OPENMP_TASK_FLAG",
    "ENUM_OPENMP_TASK_STATUS",
    "ENUM_OPENMP_THREAD",
    "ENUM_OPENMP_WORK",
    "ENUM_PMU_EVENT_SOURCE",
    "ENUM_PMU_UNIT_TYPE",
    "ENUM_SAMPLING_THREAD_STATE",
    "ENUM_SCHEDULING_THREAD_BLOCK",
    "ENUM_SLI_TRANSER",
    "ENUM_STACK_UNWIND_METHOD",
    "ENUM_VIDEO_ENGINE_CODEC",
    "ENUM_VIDEO_ENGINE_TYPE",
    "ENUM_VULKAN_PIPELINE_CREATION_FLAGS",
    "ENUM_WDDM_ENGINE_TYPE",
    "ENUM_WDDM_INTERRUPT_TYPE",
    "ENUM_WDDM_PACKET_TYPE",
    "ENUM_WDDM_PAGING_QUEUE_TYPE",
    "ENUM_WDDM_VIDMM_OP_TYPE",
    "META_DATA_CAPTURE",
    "META_DATA_EXPORT",
    "NVTX_EVENTS",
    "NVTX_PAYLOAD_ENUMS",
    "NVTX_PAYLOAD_ENUM_ENTRIES",
    "NVTX_PAYLOAD_SCHEMAS",
    "NVTX_PAYLOAD_SCHEMA_ENTRIES",
    "OSRT_API",
    "OSRT_CALLCHAINS",
    "PROCESSES",
    "PROFILER_OVERHEAD",
    "ProcessStreams",
    "StringIds",
    "TARGET_INFO_CUDA_CONTEXT_INFO",
    "TARGET_INFO_CUDA_STREAM",
    "TARGET_INFO_GPU",
    "TARGET_INFO_NIC_INFO",
    "TARGET_INFO_SESSION_START_TIME",
    "TARGET_INFO_SYSTEM_ENV",
    "ThreadNames"
  ],
  "total": {
    "graph_trace": {
      "present": false
    },
    "kernel": {
      "count": 1029202,
      "duration_s": 49.045215256,
      "present": true
    },
    "memcpy": {
      "bytes": 169475336520,
      "count": 182706,
      "duration_s": 10.995759085,
      "present": true
    },
    "memset": {
      "count": 340,
      "duration_s": 0.000568857,
      "present": true
    },
    "nccl_kernel": {
      "count": 3080,
      "duration_s": 0.880164439,
      "present": true
    },
    "nccl_nvtx": {
      "count": 708,
      "end_ns": 129122910967,
      "present": true,
      "start_ns": 66778982220
    },
    "runtime": {
      "count": 660482,
      "duration_s": 66.348905756,
      "present": true
    },
    "sync": {
      "count": 71902,
      "duration_s": 54.831505032,
      "present": true
    },
    "top_kernels": [
      {
        "count": 1505,
        "duration_s": 19.214749054,
        "name": "_grouped_fp4_w13_kernel"
      },
      {
        "count": 1505,
        "duration_s": 12.993828139,
        "name": "_grouped_fp4_linear_kernel"
      },
      {
        "count": 1435,
        "duration_s": 4.599514767,
        "name": "void <unnamed>::sparse_attention_kernel<(bool)1>(<unnamed>::SparseAttentionParams)"
      },
      {
        "count": 672,
        "duration_s": 1.865503735,
        "name": "_indexer_bf16_logits_kernel"
      },
      {
        "count": 74282,
        "duration_s": 1.604906511,
        "name": "void at::native::unrolled_elementwise_kernel<at::native::direct_copy_kernel_cuda(at::TensorIteratorBase &)::[lambda() (instance 3)]::operator ()() const::[lambda() (instance 7)]::operator ()() const::[lambda(float) (instance 1)], std::array<char *, (unsigned long)2>, (int)4, TrivialOffsetCalculator<(int)1, unsigned int>, TrivialOffsetCalculator<(int)1, unsigned int>, at::native::memory::LoadWithCast<(int)1>, at::native::memory::StoreWithCast<(int)1>>(int, T1, T2, T4, T5, T6, T7)"
      },
      {
        "count": 9065,
        "duration_s": 1.192512722,
        "name": "void at::native::elementwise_kernel<(int)128, (int)4, void at::native::gpu_kernel_impl_nocast<at::native::BinaryFunctor<c10::BFloat16, c10::BFloat16, c10::BFloat16, at::native::binary_internal::MulFunctor<float>>>(at::TensorIteratorBase &, const T1 &)::[lambda(int) (instance 1)]>(int, T3)"
      },
      {
        "count": 59954,
        "duration_s": 0.806744875,
        "name": "void at::native::elementwise_kernel<(int)128, (int)2, void at::native::gpu_kernel_impl_nocast<at::native::direct_copy_kernel_cuda(at::TensorIteratorBase &)::[lambda() (instance 3)]::operator ()() const::[lambda() (instance 7)]::operator ()() const::[lambda(float) (instance 1)]>(at::TensorIteratorBase &, const T1 &)::[lambda(int) (instance 1)]>(int, T3)"
      },
      {
        "count": 1540,
        "duration_s": 0.642699997,
        "name": "ncclDevKernel_AllReduce_Sum_bf16_RING_LL(ncclDevKernelArgsStorage<(unsigned long)4096>)"
      },
      {
        "count": 6055,
        "duration_s": 0.386711179,
        "name": "void at::native::reduce_kernel<(int)128, (int)4, at::native::ReduceOp<c10::BFloat16, at::native::func_wrapper_t<c10::BFloat16, at::native::sum_functor<c10::BFloat16, float, c10::BFloat16>::operator ()(at::TensorIterator &)::[lambda(float, float) (instance 1)]>, unsigned int, c10::BFloat16, (int)4, (int)4>>(T3)"
      },
      {
        "count": 130165,
        "duration_s": 0.372598605,
        "name": "void at::native::elementwise_kernel<(int)128, (int)2, void at::native::gpu_kernel_impl_nocast<at::native::BinaryFunctor<float, float, float, at::native::binary_internal::DivFunctor<float>>>(at::TensorIteratorBase &, const T1 &)::[lambda(int) (instance 1)]>(int, T3)"
      },
      {
        "count": 21796,
        "duration_s": 0.338906926,
        "name": "void at::native::vectorized_elementwise_kernel<(int)4, at::native::CUDAFunctor_add<float>, std::array<char *, (unsigned long)3>>(int, T2, T3)"
      },
      {
        "count": 33125,
        "duration_s": 0.324612118,
        "name": "void at::native::elementwise_kernel<(int)128, (int)2, void at::native::gpu_kernel_impl_nocast<at::native::BinaryFunctor<float, float, float, at::native::binary_internal::MulFunctor<float>>>(at::TensorIteratorBase &, const T1 &)::[lambda(int) (instance 1)]>(int, T3)"
      },
      {
        "count": 44217,
        "duration_s": 0.316869203,
        "name": "void at::native::vectorized_elementwise_kernel<(int)4, at::native::bfloat16_copy_kernel_cuda(at::TensorIteratorBase &)::[lambda(float) (instance 1)], std::array<char *, (unsigned long)2>>(int, T2, T3)"
      },
      {
        "count": 8288,
        "duration_s": 0.287677495,
        "name": "void at::native::vectorized_elementwise_kernel<(int)4, void at::native::<unnamed>::pow_tensor_scalar_kernel_impl<float, float>(at::TensorIteratorBase &, T2)::[lambda(float) (instance 1)], std::array<char *, (unsigned long)2>>(int, T2, T3)"
      },
      {
        "count": 13437,
        "duration_s": 0.239149247,
        "name": "void at::native::vectorized_elementwise_kernel<(int)4, at::native::BinaryFunctor<float, float, float, at::native::binary_internal::MulFunctor<float>>, std::array<char *, (unsigned long)3>>(int, T2, T3)"
      },
      {
        "count": 1505,
        "duration_s": 0.235938315,
        "name": "ncclDevKernel_AllReduce_Sum_f32_RING_LL(ncclDevKernelArgsStorage<(unsigned long)4096>)"
      },
      {
        "count": 510,
        "duration_s": 0.222469715,
        "name": "ampere_bf16_s16816gemm_bf16_128x256_ldg8_f2f_stages_64x3_tn"
      },
      {
        "count": 61626,
        "duration_s": 0.221968484,
        "name": "void at::native::reduce_kernel<(int)128, (int)4, at::native::ReduceOp<float, at::native::func_wrapper_t<float, at::native::sum_functor<float, float, float>::operator ()(at::TensorIterator &)::[lambda(float, float) (instance 1)]>, unsigned int, float, (int)4, (int)4>>(T3)"
      },
      {
        "count": 133238,
        "duration_s": 0.213366737,
        "name": "void at::native::vectorized_elementwise_kernel<(int)4, at::native::CUDAFunctorOnSelf_add<float>, std::array<char *, (unsigned long)2>>(int, T2, T3)"
      },
      {
        "count": 174,
        "duration_s": 0.193989848,
        "name": "ampere_sgemm_32x128_tn"
      }
    ],
    "top_nvtx": [
      {
        "count": 696,
        "end_ns": 125471183244,
        "name": "ncclAllReduce",
        "start_ns": 67391418483
      },
      {
        "count": 200,
        "end_ns": 128604426600,
        "name": "cub::DeviceSelect::Flagged",
        "start_ns": 78095753460
      },
      {
        "count": 200,
        "end_ns": 128604380734,
        "name": "cub::DeviceReduce::Sum",
        "start_ns": 78095638694
      },
      {
        "count": 64,
        "end_ns": 128477432384,
        "name": "Sampler",
        "start_ns": 100259772462
      },
      {
        "count": 34,
        "end_ns": 128605276163,
        "name": "cub::DeviceSelect::Unique",
        "start_ns": 78124377595
      },
      {
        "count": 32,
        "end_ns": 128423691722,
        "name": "cub::DeviceScan::InclusiveScan",
        "start_ns": 78132312063
      },
      {
        "count": 30,
        "end_ns": 128426170209,
        "name": "batch_prepare:decode:bs4",
        "start_ns": 100732888174
      },
      {
        "count": 30,
        "end_ns": 128477693083,
        "name": "batch_forward_enqueue:decode:bs4:padded4",
        "start_ns": 100737995091
      },
      {
        "count": 30,
        "end_ns": 128599763586,
        "name": "batch_forward:decode:bs4:padded4",
        "start_ns": 100737991023
      },
      {
        "count": 24,
        "end_ns": 128605240286,
        "name": "cub::DeviceRadixSort",
        "start_ns": 78108385076
      },
      {
        "count": 8,
        "end_ns": 125472305217,
        "name": "ncclAllGather",
        "start_ns": 74018162470
      },
      {
        "count": 8,
        "end_ns": 125471742602,
        "name": "dsv4.model.hc_head",
        "start_ns": 74012630026
      },
      {
        "count": 8,
        "end_ns": 104652164026,
        "name": "dsv4.model.hc_expand",
        "start_ns": 68050161479
      },
      {
        "count": 8,
        "end_ns": 125471931447,
        "name": "dsv4.model.final_norm",
        "start_ns": 74013053770
      },
      {
        "count": 8,
        "end_ns": 104652058087,
        "name": "dsv4.model.embed",
        "start_ns": 66660118400
      },
      {
        "count": 8,
        "end_ns": 125472409713,
        "name": "dsv4.lm_head",
        "start_ns": 74013252863
      },
      {
        "count": 8,
        "end_ns": 109077607539,
        "name": "dsv4.layer9.mlp_input_norm",
        "start_ns": 73530188215
      },
      {
        "count": 8,
        "end_ns": 109079723947,
        "name": "dsv4.layer9.mlp.shared",
        "start_ns": 73531375661
      },
      {
        "count": 8,
        "end_ns": 109078563571,
        "name": "dsv4.layer9.mlp.routed",
        "start_ns": 73530707779
      },
      {
        "count": 8,
        "end_ns": 109079855123,
        "name": "dsv4.layer9.mlp.reduce_once",
        "start_ns": 73532652406
      }
    ],
    "top_runtime": [
      {
        "count": 68178,
        "duration_s": 50.792006468,
        "name": "cudaStreamSynchronize_v3020"
      },
      {
        "count": 77,
        "duration_s": 4.08214767,
        "name": "cudaDeviceSynchronize_v3020"
      },
      {
        "count": 310923,
        "duration_s": 3.292950191,
        "name": "cudaLaunchKernel_v7000"
      },
      {
        "count": 179140,
        "duration_s": 1.565984152,
        "name": "cudaMemcpyAsync_v3020"
      },
      {
        "count": 30,
        "duration_s": 1.560166839,
        "name": "cudaGraphLaunch_v10000"
      },
      {
        "count": 2880,
        "duration_s": 0.946761185,
        "name": "cudaThreadExchangeStreamCaptureMode_v10010"
      },
      {
        "count": 49,
        "duration_s": 0.944202078,
        "name": "cuModuleLoadData"
      },
      {
        "count": 29,
        "duration_s": 0.938227538,
        "name": "cudaHostAlloc_v3020"
      },
      {
        "count": 3,
        "duration_s": 0.619923992,
        "name": "cudaGraphInstantiateWithFlags_v11040"
      },
      {
        "count": 500,
        "duration_s": 0.35362917,
        "name": "cudaMalloc_v3020"
      },
      {
        "count": 48,
        "duration_s": 0.303696341,
        "name": "cuMemExportToShareableHandle"
      },
      {
        "count": 3,
        "duration_s": 0.171659331,
        "name": "cudaGraphExecDestroy_v10000"
      },
      {
        "count": 194,
        "duration_s": 0.150115187,
        "name": "cuMemSetAccess"
      },
      {
        "count": 48,
        "duration_s": 0.129648482,
        "name": "cuMemImportFromShareableHandle"
      },
      {
        "count": 226,
        "duration_s": 0.081468072,
        "name": "cudaFree_v3020"
      },
      {
        "count": 147,
        "duration_s": 0.080524385,
        "name": "cuMemCreate"
      },
      {
        "count": 15,
        "duration_s": 0.057186695,
        "name": "cuLibraryLoadData"
      },
      {
        "count": 73489,
        "duration_s": 0.04130136,
        "name": "cudaStreamGetCaptureInfo_v2_v11030"
      },
      {
        "count": 5083,
        "duration_s": 0.039882468,
        "name": "cuLaunchKernelEx"
      },
      {
        "count": 3,
        "duration_s": 0.0364609,
        "name": "cudaGraphDestroy_v10000"
      }
    ],
    "window_found": null,
    "window_name": null,
    "window_ns": null
  }
}
